pynterlinear/__init__.py
pynterlinear/csv2latex.py
pynterlinear/csv2word.py
pynterlinear/data/glossing.txt
pynterlinear-0.0.2.dist-info/LICENSE
pynterlinear-0.0.2.dist-info/METADATA
pynterlinear-0.0.2.dist-info/WHEEL
pynterlinear-0.0.2.dist-info/top_level.txt
pynterlinear-0.0.2.dist-info/RECORD
